{
  "generatedAt": "2026-07-08T19:21:27.738Z",
  "switzerland": [
    {
      "title": "Vardavar",
      "url": "https://armenopole.com/vardavar-switzerland.html",
      "location": "Genève",
      "date": "2026-07-12T10:30:00.000Z",
      "rawDate": "JUL 12 10:30",
      "country": "switzerland"
    },
    {
      "title": "Western Armenian Courses",
      "url": "https://armenopole.com/western-armenian-courses-switzerland-2026-7-18.html",
      "location": "Suisse",
      "date": "2026-07-18T23:59:00.000Z",
      "rawDate": "JUL 18 23:59",
      "country": "switzerland"
    },
    {
      "title": "Soirée Arménienne",
      "url": "https://armenopole.com/soiree-armenienne-switzerland.html",
      "location": "Genève",
      "date": "2026-08-04T19:00:00.000Z",
      "rawDate": "AOÛ 4 19:00",
      "country": "switzerland"
    },
    {
      "title": "Musique arménienne",
      "url": "https://armenopole.com/musique-armenienne-switzerland.html",
      "location": "Valais",
      "date": "2026-08-07T18:00:00.000Z",
      "rawDate": "AOÛ 7 18:00",
      "country": "switzerland"
    },
    {
      "title": "Berd ensemble at FIFO",
      "url": "https://armenopole.com/berd-ensemble-at-fifo.html",
      "location": "Valais",
      "date": "2026-08-08T17:00:00.000Z",
      "rawDate": "AOÛ 8 17:00",
      "country": "switzerland"
    },
    {
      "title": "Armenian Autumn at Restaurant Estia, Zurich",
      "url": "https://armenopole.com/armenian-autumn-at-restaurant-estia-zurich.html",
      "location": "Zurich",
      "date": "2026-09-30T19:00:00.000Z",
      "rawDate": "SEP 30 19:00",
      "country": "switzerland"
    },
    {
      "title": "Armenian Autumn at Restaurant Estia, Zurich",
      "url": "https://armenopole.com/armenian-autumn-at-restaurant-estia-zurich-switzerland.html",
      "location": "Zurich",
      "date": "2026-10-01T19:00:00.000Z",
      "rawDate": "OCT 1 19:00",
      "country": "switzerland"
    },
    {
      "title": "Ballet Sheherezade - Khachaturian, Korskakov",
      "url": "https://armenopole.com/ballet-sheherezade-khachaturian-korskakov-switzerland-2026-10-18.html",
      "location": "Zurich",
      "date": "2026-10-11T15:00:00.000Z",
      "rawDate": "OCT 11 15:00",
      "country": "switzerland"
    },
    {
      "title": "Ballet Sheherezade - Khachaturian, Korskakov",
      "url": "https://armenopole.com/ballet-sheherezade-khachaturian-korskakov-switzerland.html",
      "location": "Vaud",
      "date": "2026-11-28T18:30:00.000Z",
      "rawDate": "NOV 28 18:30",
      "country": "switzerland"
    },
    {
      "title": "Ballet Sheherezade - Khachaturian, Korskakov",
      "url": "https://armenopole.com/ballet-sheherezade-khachaturian-korskakov.html",
      "location": "Genève",
      "date": "2026-11-29T16:30:00.000Z",
      "rawDate": "NOV 29 16:30",
      "country": "switzerland"
    },
    {
      "title": "Salon goût et terroir",
      "url": "https://armenopole.com/salon-gout-et-terroir.html",
      "location": "Fribourg",
      "date": "2026-12-02T09:00:00.000Z",
      "rawDate": "DÉC 2 9:00",
      "country": "switzerland"
    }
  ],
  "world": [
    {
      "title": "Tanja Becker-Bender & Sofya Melikyan",
      "url": "https://armenopole.com/tanja-becker-bender-sofya-melikyan.html",
      "location": "Grand-Est",
      "date": "2026-07-08T19:00:00.000Z",
      "rawDate": "JUL 8 19:00",
      "country": "france"
    },
    {
      "title": "Soirée autour de l'Arménie - Festival Les Beaux Jours de Belloc",
      "url": "https://armenopole.com/soiree-autour-de-l-armenie-festival-les-beaux-jours-de-belloc.html",
      "location": "Nouvelle-Aquitaine",
      "date": "2026-07-08T20:00:00.000Z",
      "rawDate": "JUL 8 20:00",
      "country": "france"
    },
    {
      "title": "Hayrik: A New Project by Yelaket USA",
      "url": "https://armenopole.com/hayrik-a-new-project-by-yelaket-usa.html",
      "location": "California",
      "date": "2026-07-09T19:00:00.000Z",
      "rawDate": "JUL 9 19:00",
      "country": "usa"
    },
    {
      "title": "Projection au Ciné-Meyzieu - Le CNMA présente Retour à Babylone, en partenariat avec l'association Babylone",
      "url": "https://armenopole.com/projection-au-cine-meyzieu-le-cnma-presente-retour-a-babylone-en-partenariat-avec-l-association-babylone.html",
      "location": "Auvergne-Rhône-Alpes",
      "date": "2026-07-09T20:00:00.000Z",
      "rawDate": "JUL 9 20:00",
      "country": "france"
    },
    {
      "title": "YourSpace@Hayashen – Dance with Armenian Alphabet Workshop",
      "url": "https://armenopole.com/ccumdhjc.html",
      "location": "Angleterre",
      "date": "2026-07-10T18:30:00.000Z",
      "rawDate": "JUL 10 18:30",
      "country": "unitedkingdom"
    },
    {
      "title": "BAEDEZ family dinner",
      "url": "https://armenopole.com/baedez-family-dinner.html",
      "location": "California",
      "date": "2026-07-10T19:00:00.000Z",
      "rawDate": "JUL 10 19:00",
      "country": "usa"
    },
    {
      "title": "A Rare Collection Featuring Works by Samvel Sevada & Artashes Hunanian",
      "url": "https://armenopole.com/a-rare-collection-featuring-works-by-samvel-sevada-artashes-hunanian.html",
      "location": "California",
      "date": "2026-07-10T19:00:00.000Z",
      "rawDate": "JUL 10 19:00",
      "country": "usa"
    },
    {
      "title": "Marine Manasian Концерт",
      "url": "https://armenopole.com/5ei62ppk.html",
      "location": "Russie",
      "date": "2026-07-10T20:00:00.000Z",
      "rawDate": "JUL 10 20:00",
      "country": "russia"
    },
    {
      "title": "Heartbeats of a Land",
      "url": "https://armenopole.com/heartbeats-of-a-land.html",
      "location": "Beyrouth",
      "date": "2026-07-10T20:00:00.000Z",
      "rawDate": "JUL 10 20:00",
      "country": "lebanon"
    },
    {
      "title": "🎻 SYNERGY by Emil Khachaturyan",
      "url": "https://armenopole.com/pgpu0xpy.html",
      "location": "Ontario",
      "date": "2026-07-10T20:00:00.000Z",
      "rawDate": "JUL 10 20:00",
      "country": "canada"
    }
  ]
}
